commonMethods_zhaozl/__init__.py
commonMethods_zhaozl/__version__.py
commonMethods_zhaozl/core.py
commonMethods_zhaozl/toolbox/Method_bounceAnalyzer.py
commonMethods_zhaozl/toolbox/Method_bpNetworkRun.py
commonMethods_zhaozl/toolbox/Method_bpNetworkTrain.py
commonMethods_zhaozl/toolbox/Method_comtradeParse.py
commonMethods_zhaozl/toolbox/Method_evennessDetermine.py
commonMethods_zhaozl/toolbox/Method_mysqlOperator.py
commonMethods_zhaozl/toolbox/Method_processBar.py
commonMethods_zhaozl/toolbox/Method_timeTrans.py
commonMethods_zhaozl/toolbox/Method_trendAnalyzer.py
commonMethods_zhaozl/toolbox/__init__.py
commonMethods_zhaozl-3.14.dist-info/LICENSE
commonMethods_zhaozl-3.14.dist-info/METADATA
commonMethods_zhaozl-3.14.dist-info/WHEEL
commonMethods_zhaozl-3.14.dist-info/top_level.txt
commonMethods_zhaozl-3.14.dist-info/RECORD
