Metadata-Version: 2.1
Name: commonMethods-zhaozl
Version: 3.14
Summary: timeTrans code2Name mysqlOperator printWithColor bpNetworkTrain bpNetworkRun comtradeParse processBar trendAnalyzer bounceAnalyzer evennessDetermine... by zhaozl.
Home-page: UNKNOWN
Author: zhaozl1123
Author-email: 545362989@qq.com
License: MIT
Platform: UNKNOWN
Classifier: License :: OSI Approved :: MIT License
Classifier: Programming Language :: Python
Classifier: Programming Language :: Python :: 3
Classifier: Programming Language :: Python :: 3.6
Classifier: Programming Language :: Python :: Implementation :: CPython
Classifier: Programming Language :: Python :: Implementation :: PyPy
Requires-Python: >=3.7.0
Requires-Dist: pandas (==1.1.0)
Requires-Dist: matplotlib (==3.3.0)
Requires-Dist: sklearn (==0.0)
Requires-Dist: PyMySQL (==0.10.0)
Requires-Dist: numpy (==1.18.5)
Requires-Dist: joblib (==0.16.0)
Requires-Dist: tensorflow (==2.1.0)
